RTL_design/src/credit_manager.v
// credit_manager.v — Global credit pool with backpressure
// Up/down saturating counter. Decrement on SQ submit, increment on CQ complete.
// Simultaneous inc+dec cancels out. Stall signal when credits=0.

module credit_manager #(
    parameter CREDITS_MAX = 64
) (
    input  wire clk,
    input  wire rst_n,

    // From SQ Engine
    input  wire credit_dec,
    // From CQ Engine
    input  wire credit_inc,

    // To SQ Engine
    output wire credit_avail,
    // To MMIO decoder (UNCORE_STATUS[31:0])
    output wire [31:0] credit_count,
    // To stat counters
    output wire stat_credit_stall
);

    // Width sufficient to hold CREDITS_MAX
    localparam CW = $clog2(CREDITS_MAX + 1);

    reg [CW-1:0] credits;

    // Credit available when count > 0
    assign credit_avail = (credits != 0);

    // Export as 32-bit for status register
    assign credit_count = {{(32-CW){1'b0}}, credits};

    // Stall: dec requested but credits already 0
    assign stat_credit_stall = credit_dec & ~credit_avail;

    always @(posedge clk or negedge rst_n) begin
        if (!rst_n) begin
            credits <= CREDITS_MAX[CW-1:0];
        end else begin
            case ({credit_inc, credit_dec})
                2'b10: begin // increment only
                    if (credits < CREDITS_MAX[CW-1:0])
                        credits <= credits + 1'b1;
                end
                2'b01: begin // decrement only
                    if (credits > 0)
                        credits <= credits - 1'b1;
                end
                2'b11: begin // simultaneous — no change
                    credits <= credits;
                end
                default: begin
                    credits <= credits;
                end
            endcase
        end
    end

endmodule

RTL_design/tb/tb_credit_manager.v
// tb_credit_manager.v — Self-checking testbench for credit_manager
`timescale 1ns / 1ps

module tb_credit_manager;

    parameter CREDITS_MAX = 4; // Small for fast testing

    reg  clk, rst_n;
    reg  credit_dec, credit_inc;
    wire credit_avail;
    wire [31:0] credit_count;
    wire stat_credit_stall;

    integer errors = 0;
    integer test_num = 0;

    credit_manager #(.CREDITS_MAX(CREDITS_MAX)) dut (
        .clk(clk), .rst_n(rst_n),
        .credit_dec(credit_dec), .credit_inc(credit_inc),
        .credit_avail(credit_avail),
        .credit_count(credit_count),
        .stat_credit_stall(stat_credit_stall)
    );

    // Clock: 1 GHz = 1 ns period
    always #0.5 clk = ~clk;

    task check(input [31:0] exp_count, input exp_avail, input [127:0] msg);
        begin
            if (credit_count !== exp_count || credit_avail !== exp_avail) begin
                $display("FAIL [T%0d] %0s: count=%0d (exp %0d) avail=%0b (exp %0b)",
                         test_num, msg, credit_count, exp_count, credit_avail, exp_avail);
                errors = errors + 1;
            end else begin
                $display("PASS [T%0d] %0s", test_num, msg);
            end
        end
    endtask

    initial begin
        $dumpfile("tb_credit_manager.vcd");
        $dumpvars(0, tb_credit_manager);

        clk = 0; rst_n = 0; credit_dec = 0; credit_inc = 0;
        #2; rst_n = 1; #1;

        // T1: After reset, credits = CREDITS_MAX
        test_num = 1;
        check(CREDITS_MAX, 1, "reset value");

        // T2: Decrement to 0
        test_num = 2;
        repeat (CREDITS_MAX) begin
            credit_dec = 1; @(posedge clk); #0.1;
        end
        credit_dec = 0; @(posedge clk); #0.1;
        check(0, 0, "decremented to zero");

        // T3: Stall on further decrement
        test_num = 3;
        credit_dec = 1; @(posedge clk); #0.1;
        if (stat_credit_stall !== 1) begin
            $display("FAIL [T3] stall not asserted at zero");
            errors = errors + 1;
        end else begin
            $display("PASS [T3] stall asserted at zero");
        end
        credit_dec = 0;
        check(0, 0, "no underflow");

        // T4: Increment back to max
        test_num = 4;
        repeat (CREDITS_MAX) begin
            credit_inc = 1; @(posedge clk); #0.1;
        end
        credit_inc = 0; @(posedge clk); #0.1;
        check(CREDITS_MAX, 1, "incremented to max");

        // T5: No overflow past max
        test_num = 5;
        credit_inc = 1; @(posedge clk); #0.1;
        credit_inc = 0; @(posedge clk); #0.1;
        check(CREDITS_MAX, 1, "no overflow past max");

        // T6: Simultaneous inc + dec = no change
        test_num = 6;
        credit_dec = 1; @(posedge clk); #0.1; // dec to MAX-1
        credit_dec = 0; @(posedge clk); #0.1;
        check(CREDITS_MAX - 1, 1, "dec to MAX-1");
        credit_inc = 1; credit_dec = 1;
        @(posedge clk); #0.1;
        credit_inc = 0; credit_dec = 0;
        @(posedge clk); #0.1;
        check(CREDITS_MAX - 1, 1, "simultaneous inc+dec no change");

        // Summary
        $display("---");
        if (errors == 0)
            $display("credit_manager: ALL TESTS PASSED");
        else
            $display("credit_manager: %0d ERRORS", errors);
        $finish;
    end

endmodule

RTL_design/tb_credit_manager.vcd
$date
	Mon Apr 13 22:26:32 2026
$end
$version
	Icarus Verilog
$end
$timescale
	1ps
$end
$scope module tb_credit_manager $end
$var wire 1 ! stat_credit_stall $end
$var wire 32 " credit_count [31:0] $end
$var wire 1 # credit_avail $end
$var reg 1 $ clk $end
$var reg 1 % credit_dec $end
$var reg 1 & credit_inc $end
$var reg 1 ' rst_n $end
$var integer 32 ( errors [31:0] $end
$var integer 32 ) test_num [31:0] $end
$scope module dut $end
$var wire 1 $ clk $end
$var wire 1 % credit_dec $end
$var wire 1 & credit_inc $end
$var wire 1 ' rst_n $end
$var wire 1 ! stat_credit_stall $end
$var wire 32 * credit_count [31:0] $end
$var wire 1 # credit_avail $end
$var reg 3 + credits [2:0] $end
$upscope $end
$scope task check $end
$var reg 1 , exp_avail $end
$var reg 32 - exp_count [31:0] $end
$var reg 128 . msg [127:0] $end
$upscope $end
$upscope $end
$enddefinitions $end
#0
$dumpvars
bx .
bx -
x,
b100 +
b100 *
b0 )
b0 (
0'
0&
0%
0$
1#
b100 "
0!
$end
#500
1$
#1000
0$
#1500
1$
#2000
0$
1'
#2500
1$
#3000
0$
1%
b111001001100101011100110110010101110100001000000111011001100001011011000111010101100101 .
1,
b100 -
b10 )
#3500
b11 "
b11 *
b11 +
1$
#4000
0$
#4500
b10 "
b10 *
b10 +
1$
#5000
0$
#5500
b1 "
b1 *
b1 +
1$
#6000
0$
#6500
1!
0#
b0 "
b0 *
b0 +
1$
#6600
0!
0%
#7000
0$
#7500
1$
#7600
1!
1%
b11 )
b1110010011001010110110101100101011011100111010001100101011001000010000001110100011011110010000001111010011001010111001001101111 .
0,
b0 -
#8000
0$
#8500
1$
#8600
0!
1&
b100 )
b11011100110111100100000011101010110111001100100011001010111001001100110011011000110111101110111 .
0%
#9000
0$
#9500
1#
b1 "
b1 *
b1 +
1$
#10000
0$
#10500
b10 "
b10 *
b10 +
1$
#11000
0$
#11500
b11 "
b11 *
b11 +
1$
#12000
0$
#12500
b100 "
b100 *
b100 +
1$
#12600
0&
#13000
0$
#13500
1$
#13600
1&
b101 )
b1100011011100100110010101101101011001010110111001110100011001010110010000100000011101000110111100100000011011010110000101111000 .
1,
b100 -
#14000
0$
#14500
1$
#14600
0&
#15000
0$
#15500
1$
#15600
1%
b110 )
b1110110011001010111001001100110011011000110111101110111001000000111000001100001011100110111010000100000011011010110000101111000 .
#16000
0$
#16500
b11 "
b11 *
b11 +
1$
#16600
0%
#17000
0$
#17500
1$
#17600
1%
1&
b11001000110010101100011001000000111010001101111001000000100110101000001010110000010110100110001 .
b11 -
#18000
0$
#18500
1$
#18600
0%
0&
#19000
0$
#19500
1$
#19600
b1101110011000110010101101100100011001010110001100100000011011100110111100100000011000110110100001100001011011100110011101100101 .
