RTL_design/src/stat_counters.v
// stat_counters.v — Telemetry accumulation for IO-Uncore
// 10 x 64-bit saturating counters, pulse-increment interface, address-read export.

module stat_counters #(
    parameter NUM_COUNTERS = 10
) (
    input  wire clk,
    input  wire rst_n,

    // Pulse inputs (active-high, one per counter)
    input  wire [NUM_COUNTERS-1:0] stat_inc,

    // Read interface
    input  wire [3:0]  stat_rd_addr,  // counter index (0..NUM_COUNTERS-1)
    output wire [63:0] stat_rd_data,  // counter value

    // Bulk reset (clear all counters)
    input  wire stat_reset
);

    reg [63:0] counters [0:NUM_COUNTERS-1];

    integer i;

    // Read: combinational mux
    assign stat_rd_data = (stat_rd_addr < NUM_COUNTERS) ?
                          counters[stat_rd_addr] : 64'd0;

    always @(posedge clk or negedge rst_n) begin
        if (!rst_n || stat_reset) begin
            for (i = 0; i < NUM_COUNTERS; i = i + 1)
                counters[i] <= 64'd0;
        end else begin
            for (i = 0; i < NUM_COUNTERS; i = i + 1) begin
                if (stat_inc[i] && counters[i] != {64{1'b1}})
                    counters[i] <= counters[i] + 64'd1;
            end
        end
    end

endmodule

RTL_design/tb/tb_stat_counters.v
// tb_stat_counters.v — Self-checking testbench for stat_counters
`timescale 1ns / 1ps

module tb_stat_counters;

    parameter NUM_COUNTERS = 10;

    reg  clk, rst_n;
    reg  [NUM_COUNTERS-1:0] stat_inc;
    reg  [3:0]  stat_rd_addr;
    wire [63:0] stat_rd_data;
    reg  stat_reset;

    integer errors = 0;

    stat_counters #(.NUM_COUNTERS(NUM_COUNTERS)) dut (
        .clk(clk), .rst_n(rst_n),
        .stat_inc(stat_inc),
        .stat_rd_addr(stat_rd_addr),
        .stat_rd_data(stat_rd_data),
        .stat_reset(stat_reset)
    );

    always #0.5 clk = ~clk;

    task check_counter(input [3:0] idx, input [63:0] expected, input [127:0] msg);
        begin
            stat_rd_addr = idx;
            #0.1;
            if (stat_rd_data !== expected) begin
                $display("FAIL %0s: counter[%0d]=%0d (exp %0d)", msg, idx, stat_rd_data, expected);
                errors = errors + 1;
            end else begin
                $display("PASS %0s", msg);
            end
        end
    endtask

    initial begin
        $dumpfile("tb_stat_counters.vcd");
        $dumpvars(0, tb_stat_counters);

        clk = 0; rst_n = 0; stat_inc = 0; stat_rd_addr = 0; stat_reset = 0;
        #2; rst_n = 1; #1;

        // T1: All counters zero after reset
        check_counter(0, 0, "reset counter 0");
        check_counter(9, 0, "reset counter 9");

        // T2: Increment counter 0 three times
        stat_inc = 10'b0000000001;
        @(posedge clk); @(posedge clk); @(posedge clk); #0.1;
        stat_inc = 0; @(posedge clk); #0.1;
        check_counter(0, 3, "counter 0 incremented 3x");
        check_counter(1, 0, "counter 1 still zero");

        // T3: Increment multiple counters simultaneously
        stat_inc = 10'b0000001010; // counters 1 and 3
        @(posedge clk); @(posedge clk); #0.1;
        stat_inc = 0; @(posedge clk); #0.1;
        check_counter(1, 2, "counter 1 incremented 2x");
        check_counter(3, 2, "counter 3 incremented 2x");
        check_counter(0, 3, "counter 0 unchanged");

        // T4: Bulk reset
        stat_reset = 1; @(posedge clk); #0.1;
        stat_reset = 0; @(posedge clk); #0.1;
        check_counter(0, 0, "counter 0 after reset");
        check_counter(1, 0, "counter 1 after reset");
        check_counter(3, 0, "counter 3 after reset");

        // T5: Out-of-range read returns 0
        check_counter(4'd15, 0, "out-of-range returns 0");

        // Summary
        $display("---");
        if (errors == 0)
            $display("stat_counters: ALL TESTS PASSED");
        else
            $display("stat_counters: %0d ERRORS", errors);
        $finish;
    end

endmodule

RTL_design/tb_stat_counters.vcd
$date
	Mon Apr 13 22:28:01 2026
$end
$version
	Icarus Verilog
$end
$timescale
	1ps
$end
$scope module tb_stat_counters $end
$var wire 64 ! stat_rd_data [63:0] $end
$var reg 1 " clk $end
$var reg 1 # rst_n $end
$var reg 10 $ stat_inc [9:0] $end
$var reg 4 % stat_rd_addr [3:0] $end
$var reg 1 & stat_reset $end
$var integer 32 ' errors [31:0] $end
$scope module dut $end
$var wire 1 " clk $end
$var wire 1 # rst_n $end
$var wire 10 ( stat_inc [9:0] $end
$var wire 4 ) stat_rd_addr [3:0] $end
$var wire 1 & stat_reset $end
$var wire 64 * stat_rd_data [63:0] $end
$var integer 32 + i [31:0] $end
$upscope $end
$scope task check_counter $end
$var reg 64 , expected [63:0] $end
$var reg 4 - idx [3:0] $end
$var reg 128 . msg [127:0] $end
$upscope $end
$upscope $end
$enddefinitions $end
#0
$dumpvars
bx .
bx -
bx ,
b1010 +
b0 *
b0 )
b0 (
b0 '
0&
b0 %
b0 $
0#
0"
b0 !
$end
#500
b1010 +
1"
#1000
0"
#1500
b1010 +
1"
#2000
0"
1#
#2500
b1010 +
1"
#3000
0"
b11100100110010101110011011001010111010000100000011000110110111101110101011011100111010001100101011100100010000000110000 .
b0 ,
b0 -
#3100
b1001 %
b1001 )
b11100100110010101110011011001010111010000100000011000110110111101110101011011100111010001100101011100100010000000111001 .
b1001 -
#3200
b1 $
b1 (
#3500
b1010 +
1"
#4000
0"
#4500
b1010 +
1"
#5000
0"
#5500
b1010 +
1"
#5600
b0 $
b0 (
#6000
0"
#6500
b1010 +
1"
#6600
b11 !
b11 *
b0 %
b0 )
b110000001000000110100101101110011000110111001001100101011011010110010101101110011101000110010101100100001000000011001101111000 .
b11 ,
b0 -
#6700
b0 !
b0 *
b1 %
b1 )
b1110100011001010111001000100000001100010010000001110011011101000110100101101100011011000010000001111010011001010111001001101111 .
b0 ,
b1 -
#6800
b1010 $
b1010 (
#7000
0"
#7500
b1 !
b1 *
b1010 +
1"
#8000
0"
#8500
b10 !
b10 *
b1010 +
1"
#8600
b0 $
b0 (
#9000
0"
#9500
b1010 +
1"
#9600
b110001001000000110100101101110011000110111001001100101011011010110010101101110011101000110010101100100001000000011001001111000 .
b10 ,
#9700
b11 %
b11 )
b110011001000000110100101101110011000110111001001100101011011010110010101101110011101000110010101100100001000000011001001111000 .
b11 -
#9800
b11 !
b11 *
b0 %
b0 )
b1101110011101000110010101110010001000000011000000100000011101010110111001100011011010000110000101101110011001110110010101100100 .
b11 ,
b0 -
#9900
1&
#10000
0"
#10500
b0 !
b0 *
b1010 +
1"
#10600
0&
#11000
0"
#11500
b1010 +
1"
#11600
b1100101011100100010000000110000001000000110000101100110011101000110010101110010001000000111001001100101011100110110010101110100 .
b0 ,
#11700
b1 %
b1 )
b1100101011100100010000000110001001000000110000101100110011101000110010101110010001000000111001001100101011100110110010101110100 .
b1 -
#11800
b11 %
b11 )
b1100101011100100010000000110011001000000110000101100110011101000110010101110010001000000111001001100101011100110110010101110100 .
b11 -
#11900
b1111 %
b1111 )
b101101011100100110000101101110011001110110010100100000011100100110010101110100011101010111001001101110011100110010000000110000 .
b1111 -
