RTL_design/src/sram_arbiter.v
// sram_arbiter.v — Round-robin arbiter for shared SRAM access
// 3 requestors, 512-bit data bus, 1-cycle grant latency.
// SRAM modeled as a register array (replaced by macro in synthesis).

module sram_arbiter #(
    parameter NUM_REQUESTORS = 3,
    parameter SRAM_ADDR_WIDTH = 20,
    parameter DATA_WIDTH = 512,
    parameter SRAM_DEPTH = 1048576  // default 1M entries, overridden by top
) (
    input  wire clk,
    input  wire rst_n,

    // Requestor 0 (SQ Engine)
    input  wire                      req0_valid,
    input  wire                      req0_wr,     // 1=write, 0=read
    input  wire [SRAM_ADDR_WIDTH-1:0] req0_addr,
    input  wire [DATA_WIDTH-1:0]     req0_wdata,
    output reg                       req0_grant,
    output wire [DATA_WIDTH-1:0]     req0_rdata,

    // Requestor 1 (CQ Engine)
    input  wire                      req1_valid,
    input  wire                      req1_wr,
    input  wire [SRAM_ADDR_WIDTH-1:0] req1_addr,
    input  wire [DATA_WIDTH-1:0]     req1_wdata,
    output reg                       req1_grant,
    output wire [DATA_WIDTH-1:0]     req1_rdata,

    // Requestor 2 (DB Coalescer — typically unused, reserved)
    input  wire                      req2_valid,
    input  wire                      req2_wr,
    input  wire [SRAM_ADDR_WIDTH-1:0] req2_addr,
    input  wire [DATA_WIDTH-1:0]     req2_wdata,
    output reg                       req2_grant,
    output wire [DATA_WIDTH-1:0]     req2_rdata
);

    // SRAM storage (register array — analytical SRAM model used for area)
    reg [DATA_WIDTH-1:0] sram [0:SRAM_DEPTH-1];

    // Round-robin priority
    reg [1:0] last_grant; // 0, 1, or 2

    // Internal signals
    reg                       sel_valid;
    reg                       sel_wr;
    reg [SRAM_ADDR_WIDTH-1:0] sel_addr;
    reg [DATA_WIDTH-1:0]      sel_wdata;
    reg [1:0]                 sel_id;

    // Read data register
    reg [DATA_WIDTH-1:0] rdata_reg;

    assign req0_rdata = rdata_reg;
    assign req1_rdata = rdata_reg;
    assign req2_rdata = rdata_reg;

    // Arbitration: round-robin starting from (last_grant + 1)
    always @(*) begin
        sel_valid = 0;
        sel_wr    = 0;
        sel_addr  = 0;
        sel_wdata = 0;
        sel_id    = 0;
        req0_grant = 0;
        req1_grant = 0;
        req2_grant = 0;

        // Try three candidates in round-robin order
        if (last_grant == 2'd0) begin
            if (req1_valid) begin
                sel_valid = 1; sel_id = 1; sel_wr = req1_wr;
                sel_addr = req1_addr; sel_wdata = req1_wdata; req1_grant = 1;
            end else if (req2_valid) begin
                sel_valid = 1; sel_id = 2; sel_wr = req2_wr;
                sel_addr = req2_addr; sel_wdata = req2_wdata; req2_grant = 1;
            end else if (req0_valid) begin
                sel_valid = 1; sel_id = 0; sel_wr = req0_wr;
                sel_addr = req0_addr; sel_wdata = req0_wdata; req0_grant = 1;
            end
        end else if (last_grant == 2'd1) begin
            if (req2_valid) begin
                sel_valid = 1; sel_id = 2; sel_wr = req2_wr;
                sel_addr = req2_addr; sel_wdata = req2_wdata; req2_grant = 1;
            end else if (req0_valid) begin
                sel_valid = 1; sel_id = 0; sel_wr = req0_wr;
                sel_addr = req0_addr; sel_wdata = req0_wdata; req0_grant = 1;
            end else if (req1_valid) begin
                sel_valid = 1; sel_id = 1; sel_wr = req1_wr;
                sel_addr = req1_addr; sel_wdata = req1_wdata; req1_grant = 1;
            end
        end else begin // last_grant == 2
            if (req0_valid) begin
                sel_valid = 1; sel_id = 0; sel_wr = req0_wr;
                sel_addr = req0_addr; sel_wdata = req0_wdata; req0_grant = 1;
            end else if (req1_valid) begin
                sel_valid = 1; sel_id = 1; sel_wr = req1_wr;
                sel_addr = req1_addr; sel_wdata = req1_wdata; req1_grant = 1;
            end else if (req2_valid) begin
                sel_valid = 1; sel_id = 2; sel_wr = req2_wr;
                sel_addr = req2_addr; sel_wdata = req2_wdata; req2_grant = 1;
            end
        end
    end

    // SRAM access on clock edge
    always @(posedge clk or negedge rst_n) begin
        if (!rst_n) begin
            last_grant <= 2'd2; // start with req0 having first priority
            rdata_reg  <= {DATA_WIDTH{1'b0}};
        end else if (sel_valid) begin
            last_grant <= sel_id;
            if (sel_wr) begin
                sram[sel_addr] <= sel_wdata;
            end else begin
                rdata_reg <= sram[sel_addr];
            end
        end
    end

endmodule

RTL_design/tb/tb_sram_arbiter.v
// tb_sram_arbiter.v — Self-checking testbench for sram_arbiter
// Timing convention: present inputs at negedge, check combinatorial grants at
// negedge+1, commit on posedge.  rdata is sampled one cycle after the read grant.
`timescale 1ns / 1ps

module tb_sram_arbiter;

    parameter SRAM_ADDR_WIDTH = 8;
    parameter DATA_WIDTH = 128;
    parameter SRAM_DEPTH = 256;

    reg  clk, rst_n;
    reg  req0_valid, req0_wr;
    reg  [SRAM_ADDR_WIDTH-1:0] req0_addr;
    reg  [DATA_WIDTH-1:0] req0_wdata;
    wire req0_grant;
    wire [DATA_WIDTH-1:0] req0_rdata;

    reg  req1_valid, req1_wr;
    reg  [SRAM_ADDR_WIDTH-1:0] req1_addr;
    reg  [DATA_WIDTH-1:0] req1_wdata;
    wire req1_grant;
    wire [DATA_WIDTH-1:0] req1_rdata;

    reg  req2_valid, req2_wr;
    reg  [SRAM_ADDR_WIDTH-1:0] req2_addr;
    reg  [DATA_WIDTH-1:0] req2_wdata;
    wire req2_grant;
    wire [DATA_WIDTH-1:0] req2_rdata;

    integer errors = 0;

    sram_arbiter #(
        .NUM_REQUESTORS(3), .SRAM_ADDR_WIDTH(SRAM_ADDR_WIDTH),
        .DATA_WIDTH(DATA_WIDTH), .SRAM_DEPTH(SRAM_DEPTH)
    ) dut (
        .clk(clk), .rst_n(rst_n),
        .req0_valid(req0_valid), .req0_wr(req0_wr), .req0_addr(req0_addr),
        .req0_wdata(req0_wdata), .req0_grant(req0_grant), .req0_rdata(req0_rdata),
        .req1_valid(req1_valid), .req1_wr(req1_wr), .req1_addr(req1_addr),
        .req1_wdata(req1_wdata), .req1_grant(req1_grant), .req1_rdata(req1_rdata),
        .req2_valid(req2_valid), .req2_wr(req2_wr), .req2_addr(req2_addr),
        .req2_wdata(req2_wdata), .req2_grant(req2_grant), .req2_rdata(req2_rdata)
    );

    // 10 ns period (negedge at 5 ns = mid-cycle)
    always #5 clk = ~clk;

    task reset_inputs;
        begin
            req0_valid = 0; req0_wr = 0; req0_addr = 0; req0_wdata = 0;
            req1_valid = 0; req1_wr = 0; req1_addr = 0; req1_wdata = 0;
            req2_valid = 0; req2_wr = 0; req2_addr = 0; req2_wdata = 0;
        end
    endtask

    // Helper: wait for next negedge, apply inputs, check grants,
    //         then posedge commits to SRAM.
    // Grants are combinatorial outputs valid while inputs are asserted.
    // We check at negedge+1ns (inputs stable, combinatorial settled).

    initial begin
        $dumpfile("tb_sram_arbiter.vcd");
        $dumpvars(0, tb_sram_arbiter);

        clk = 0; rst_n = 0; reset_inputs;
        // Hold reset for 2 posedges
        @(posedge clk); @(posedge clk);
        rst_n = 1;
        @(posedge clk); // settle

        // ----------------------------------------------------------------
        // T1: Single requestor write — present at negedge, check grant,
        //     posedge commits write.
        // ----------------------------------------------------------------
        $display("--- T1: Single requestor write + read ---");
        @(negedge clk);
        req0_valid = 1; req0_wr = 1; req0_addr = 8'd10; req0_wdata = 128'hDEADBEEF;
        #1; // combinatorial settle
        if (!req0_grant) begin
            $display("FAIL T1: write grant not asserted (got g0=%b)", req0_grant);
            errors = errors + 1;
        end else $display("PASS T1: write granted");
        @(posedge clk); // commit write to SRAM
        reset_inputs;

        // Read back: present read at negedge, commit at posedge,
        // rdata is registered and available one cycle later.
        @(negedge clk);
        req0_valid = 1; req0_wr = 0; req0_addr = 8'd10;
        #1;
        if (!req0_grant) begin
            $display("FAIL T1: read grant not asserted"); errors = errors + 1;
        end
        @(posedge clk); // commit read — rdata latches at this edge
        reset_inputs;
        @(posedge clk); // rdata now stable in rdata_reg
        #1;
        if (req0_rdata !== 128'hDEADBEEF) begin
            $display("FAIL T1: readback=%h (exp DEADBEEF)", req0_rdata);
            errors = errors + 1;
        end else $display("PASS T1: readback correct");

        // ----------------------------------------------------------------
        // T2: Contention — req0 and req1 both valid.
        //     After T1 last_grant=0, so RR order: 1 -> 2 -> 0.
        //     req1 should win first; req0 wins next cycle.
        // ----------------------------------------------------------------
        $display("--- T2: Contention round-robin ---");
        @(negedge clk);
        req0_valid = 1; req0_wr = 1; req0_addr = 8'd20; req0_wdata = 128'hAAAA;
        req1_valid = 1; req1_wr = 1; req1_addr = 8'd30; req1_wdata = 128'hBBBB;
        #1;
        if (!req1_grant || req0_grant) begin
            $display("FAIL T2: req1 should win first (g0=%b g1=%b)", req0_grant, req1_grant);
            errors = errors + 1;
        end else $display("PASS T2: req1 granted first");
        @(posedge clk); // commit req1 write
        // req0 still pending; req1 de-asserted next cycle
        req1_valid = 0;
        #1;
        if (!req0_grant) begin
            $display("FAIL T2: req0 should get second grant (g0=%b)", req0_grant);
            errors = errors + 1;
        end else $display("PASS T2: req0 granted second");
        @(posedge clk); // commit req0 write
        reset_inputs;
        @(posedge clk);

        // ----------------------------------------------------------------
        // T3: Three-way contention — after T2 last_grant=0, order: 1->2->0.
        // ----------------------------------------------------------------
        $display("--- T3: Three-way contention ---");
        @(negedge clk);
        req0_valid = 1; req0_wr = 1; req0_addr = 8'd40; req0_wdata = 128'h1111;
        req1_valid = 1; req1_wr = 1; req1_addr = 8'd50; req1_wdata = 128'h2222;
        req2_valid = 1; req2_wr = 1; req2_addr = 8'd60; req2_wdata = 128'h3333;
        #1;
        if (!req1_grant || req0_grant || req2_grant) begin
            $display("FAIL T3a: req1 expected first (g0=%b g1=%b g2=%b)",
                     req0_grant, req1_grant, req2_grant);
            errors = errors + 1;
        end else $display("PASS T3a: req1 first");
        @(posedge clk);
        req1_valid = 0;
        #1;
        if (!req2_grant || req0_grant) begin
            $display("FAIL T3b: req2 expected second (g0=%b g2=%b)", req0_grant, req2_grant);
            errors = errors + 1;
        end else $display("PASS T3b: req2 second");
        @(posedge clk);
        req2_valid = 0;
        #1;
        if (!req0_grant) begin
            $display("FAIL T3c: req0 expected third (g0=%b)", req0_grant);
            errors = errors + 1;
        end else $display("PASS T3c: req0 third");
        @(posedge clk);
        reset_inputs;
        @(posedge clk);

        // ----------------------------------------------------------------
        // Summary
        // ----------------------------------------------------------------
        $display("---");
        if (errors == 0)
            $display("sram_arbiter: ALL TESTS PASSED");
        else
            $display("sram_arbiter: %0d ERRORS", errors);
        $finish;
    end

endmodule

RTL_design/tb_sram_arbiter.vcd
$date
	Mon Apr 13 22:31:36 2026
$end
$version
	Icarus Verilog
$end
$timescale
	1ps
$end
$scope module tb_sram_arbiter $end
$var wire 128 ! req2_rdata [127:0] $end
$var wire 1 " req2_grant $end
$var wire 128 # req1_rdata [127:0] $end
$var wire 1 $ req1_grant $end
$var wire 128 % req0_rdata [127:0] $end
$var wire 1 & req0_grant $end
$var reg 1 ' clk $end
$var reg 8 ( req0_addr [7:0] $end
$var reg 1 ) req0_valid $end
$var reg 128 * req0_wdata [127:0] $end
$var reg 1 + req0_wr $end
$var reg 8 , req1_addr [7:0] $end
$var reg 1 - req1_valid $end
$var reg 128 . req1_wdata [127:0] $end
$var reg 1 / req1_wr $end
$var reg 8 0 req2_addr [7:0] $end
$var reg 1 1 req2_valid $end
$var reg 128 2 req2_wdata [127:0] $end
$var reg 1 3 req2_wr $end
$var reg 1 4 rst_n $end
$var integer 32 5 errors [31:0] $end
$scope module dut $end
$var wire 1 ' clk $end
$var wire 8 6 req0_addr [7:0] $end
$var wire 128 7 req0_rdata [127:0] $end
$var wire 1 ) req0_valid $end
$var wire 128 8 req0_wdata [127:0] $end
$var wire 1 + req0_wr $end
$var wire 8 9 req1_addr [7:0] $end
$var wire 128 : req1_rdata [127:0] $end
$var wire 1 - req1_valid $end
$var wire 128 ; req1_wdata [127:0] $end
$var wire 1 / req1_wr $end
$var wire 8 < req2_addr [7:0] $end
$var wire 128 = req2_rdata [127:0] $end
$var wire 1 1 req2_valid $end
$var wire 128 > req2_wdata [127:0] $end
$var wire 1 3 req2_wr $end
$var wire 1 4 rst_n $end
$var reg 2 ? last_grant [1:0] $end
$var reg 128 @ rdata_reg [127:0] $end
$var reg 1 & req0_grant $end
$var reg 1 $ req1_grant $end
$var reg 1 " req2_grant $end
$var reg 8 A sel_addr [7:0] $end
$var reg 2 B sel_id [1:0] $end
$var reg 1 C sel_valid $end
$var reg 128 D sel_wdata [127:0] $end
$var reg 1 E sel_wr $end
$upscope $end
$scope task reset_inputs $end
$upscope $end
$upscope $end
$enddefinitions $end
#0
$dumpvars
0E
b0 D
0C
b0 B
b0 A
b0 @
b10 ?
b0 >
b0 =
b0 <
b0 ;
b0 :
b0 9
b0 8
b0 7
b0 6
b0 5
04
03
b0 2
01
b0 0
0/
b0 .
0-
b0 ,
0+
b0 *
0)
b0 (
0'
0&
b0 %
0$
b0 #
0"
b0 !
$end
#5000
1'
#10000
0'
#15000
14
1'
#20000
0'
#25000
1'
#30000
1&
b11011110101011011011111011101111 D
b1010 A
1E
1C
b11011110101011011011111011101111 *
b11011110101011011011111011101111 8
b1010 (
b1010 6
1+
1)
0'
#35000
b0 ?
0&
b0 D
b0 A
0E
0C
b0 *
b0 8
b0 (
b0 6
0+
0)
1'
#40000
1&
b1010 A
1C
b1010 (
b1010 6
1)
0'
#45000
b11011110101011011011111011101111 !
b11011110101011011011111011101111 =
b11011110101011011011111011101111 #
b11011110101011011011111011101111 :
b11011110101011011011111011101111 %
b11011110101011011011111011101111 7
b11011110101011011011111011101111 @
0&
b0 A
0C
b0 (
b0 6
0)
1'
#50000
0'
#55000
1'
#60000
1$
b1011101110111011 D
b11110 A
1E
b1 B
1C
b1011101110111011 .
b1011101110111011 ;
b11110 ,
b11110 9
1/
1-
b1010101010101010 *
b1010101010101010 8
b10100 (
b10100 6
1+
1)
0'
#65000
b1 ?
1&
0$
b0 B
b1010101010101010 D
b10100 A
1E
1C
0-
1'
#70000
0'
#75000
b0 ?
0&
b0 D
b0 A
0E
0C
b0 .
b0 ;
b0 ,
b0 9
0/
b0 *
b0 8
b0 (
b0 6
0+
0)
1'
#80000
0'
#85000
1'
#90000
1$
b10001000100010 D
b110010 A
1E
b1 B
1C
b11001100110011 2
b11001100110011 >
b111100 0
b111100 <
13
11
b10001000100010 .
b10001000100010 ;
b110010 ,
b110010 9
1/
1-
b1000100010001 *
b1000100010001 8
b101000 (
b101000 6
1+
1)
0'
#95000
b1 ?
1"
0$
b10 B
b11001100110011 D
b111100 A
1E
1C
0-
1'
#100000
0'
#105000
b10 ?
1&
0"
b0 B
b1000100010001 D
b101000 A
1E
1C
01
1'
#110000
0'
#115000
b0 ?
0&
b0 D
b0 A
0E
0C
b0 2
b0 >
b0 0
b0 <
03
b0 .
b0 ;
b0 ,
b0 9
0/
b0 *
b0 8
b0 (
b0 6
0+
0)
1'
